sqlalchemy_history/__init__.py
sqlalchemy_history/builder.py
sqlalchemy_history/exc.py
sqlalchemy_history/expression_reflector.py
sqlalchemy_history/factory.py
sqlalchemy_history/fetcher.py
sqlalchemy_history/manager.py
sqlalchemy_history/model_builder.py
sqlalchemy_history/operation.py
sqlalchemy_history/plugins/__init__.py
sqlalchemy_history/plugins/activity.py
sqlalchemy_history/plugins/base.py
sqlalchemy_history/plugins/null_delete.py
sqlalchemy_history/plugins/property_mod_tracker.py
sqlalchemy_history/plugins/transaction_changes.py
sqlalchemy_history/plugins/transaction_meta.py
sqlalchemy_history/relationship_builder.py
sqlalchemy_history/reverter.py
sqlalchemy_history/schema.py
sqlalchemy_history/table_builder.py
sqlalchemy_history/transaction.py
sqlalchemy_history/unit_of_work.py
sqlalchemy_history/utils.py
sqlalchemy_history/version.py
sqlalchemy_history-2.1.4.dist-info/LICENSE
sqlalchemy_history-2.1.4.dist-info/METADATA
sqlalchemy_history-2.1.4.dist-info/WHEEL
sqlalchemy_history-2.1.4.dist-info/RECORD
