Metadata-Version: 2.1
Name: sqlalchemy-history
Version: 2.1.4
Summary: History tracking extension for SQLAlchemy.
Home-page: https://github.com/corridor/sqlalchemy-history
License: Apache-2.0, BSD-3-Clause
Author: Corridor Platforms
Author-email: postmaster@corridorplatforms.com
Requires-Python: >=3.7,<4.0
Classifier: Intended Audience :: Developers
Classifier: License :: Other/Proprietary License
Classifier: Operating System :: OS Independent
Classifier: Programming Language :: Python
Classifier: Programming Language :: Python :: 3
Classifier: Programming Language :: Python :: 3.7
Classifier: Programming Language :: Python :: 3.8
Classifier: Programming Language :: Python :: 3.9
Classifier: Programming Language :: Python :: 3.10
Classifier: Programming Language :: Python :: 3.11
Classifier: Topic :: Software Development :: Libraries :: Python Modules
Requires-Dist: SQLAlchemy (>=1.4)
Requires-Dist: SQLAlchemy-Utils (>=0.30.12)
Requires-Dist: cached-property
Project-URL: Repository, https://github.com/corridor/sqlalchemy-history
